odoo/addons/dilve/CHANGELOG.md
odoo/addons/dilve/Readme.md
odoo/addons/dilve/__init__.py
odoo/addons/dilve/__manifest__.py
odoo/addons/dilve/dapi/__init__.py
odoo/addons/dilve/dapi/dapi.py
odoo/addons/dilve/dapi/dapi_mock.py
odoo/addons/dilve/dapi/data_classes/__init__.py
odoo/addons/dilve/dapi/data_classes/dapi_error_handler.py
odoo/addons/dilve/dapi/data_classes/get_record_list_x.py
odoo/addons/dilve/dapi/data_classes/get_record_status_x.py
odoo/addons/dilve/dapi/data_classes/get_records_x.py
odoo/addons/dilve/dapi/data_classes/get_resource_x.py
odoo/addons/dilve/dapi/thema/20250204_Thema_v1.6_es.json
odoo/addons/dilve/dapi/thema/__init__.py
odoo/addons/dilve/dapi/thema/thema.py
odoo/addons/dilve/models/__init__.py
odoo/addons/dilve/models/dilve_record.py
odoo/addons/dilve/models/res_company.py
odoo/addons/dilve/models/res_config_settings.py
odoo/addons/dilve/onix/__init__.py
odoo/addons/dilve/onix/onix2odoo.py
odoo/addons/dilve/onix/onix_book_product_3_1_reference.py
odoo/addons/dilve/onix/onix_book_product_code_lists.py
odoo/addons/dilve/onix/onix_xhtml_subset.py
odoo/addons/dilve/onix/schemas/v3.1/ONIX_BookProduct_3.1_reference.xsd
odoo/addons/dilve/onix/schemas/v3.1/ONIX_BookProduct_3.1_short.xsd
odoo/addons/dilve/onix/schemas/v3.1/ONIX_BookProduct_CodeLists.xsd
odoo/addons/dilve/onix/schemas/v3.1/ONIX_XHTML_Subset.xsd
odoo/addons/dilve/onix/schemas/v3.1/Onix3sample_refnames.xml
odoo/addons/dilve/onix/schemas/v3.1/Onix3sample_shorttags.xml
odoo/addons/dilve/sample_data/978-84-121353-3-6.xml
odoo/addons/dilve/sample_data/978-84-122365-7-6.xml
odoo/addons/dilve/sample_data/978-84-18690-63-1.xml
odoo/addons/dilve/sample_data/9788412135336.jpg
odoo/addons/dilve/sample_data/9788412236576.jpg
odoo/addons/dilve/sample_data/9788418690631.jpg
odoo/addons/dilve/sample_data/getRecordListXResponse.xml
odoo/addons/dilve/sample_data/getRecordStatusXResponse.xml
odoo/addons/dilve/security/ir.model.access.csv
odoo/addons/dilve/static/src/js/import_from_dilve_button.js
odoo_addon_dilve-17.0.1.2.0.3.dist-info/METADATA
odoo_addon_dilve-17.0.1.2.0.3.dist-info/WHEEL
odoo_addon_dilve-17.0.1.2.0.3.dist-info/top_level.txt
odoo_addon_dilve-17.0.1.2.0.3.dist-info/RECORD
