Metadata-Version: 2.1
Name: odoo-addon-dilve
Version: 17.0.1.2.0.3
Requires-Python: >=3.10
Requires-Dist: aiohttp
Requires-Dist: odoo-addon-gestion_editorial>=17.0dev,<17.1dev
Requires-Dist: odoo>=17.0a,<17.1dev
Requires-Dist: xmlschema
Requires-Dist: xsdata[cli]
Summary: =?utf-8?q?M=C3=B3dulo_para_la_integraci=C3=B3n_con_el_sistema_DILVE=2E?=
Home-page: https://simbiotica.coop/
License: AGPL-3
Author: =?utf-8?b?U2ltYmnDs3RpY2EgdGVjIFMuQ29vcC5NYWQu?=
Classifier: Programming Language :: Python
Classifier: Framework :: Odoo
Classifier: Framework :: Odoo :: 17.0
Classifier: License :: OSI Approved :: GNU Affero General Public License v3
